Workbook

Sheet Kanban
A1: ID | B1: Status | C1: Prioridade | D1: Marco | E1: Semana | F1: Período | G1: Área | H1: Tarefa | I1: Descrição / Critério de pronto | J1: Responsável sugerido | K1: Depende de
A2: T001 | B2: To Do | C2: INEGOCIÁVEL | D2: PROTÓTIPO (20/09) | E2: S1 | F2: 11/09 – 18/09 | G2: Infra | H2: Setup do projeto Unity + versionamento | I2: Projeto URP criado, Git/Plastic configurado, convenção de pastas e branch definida, todos com acesso e commit feito. | J2: Daniel | K2: —
A3: T002 | B3: To Do | C3: INEGOCIÁVEL | D3: PROTÓTIPO (20/09) | E3: S1 | F3: 11/09 – 18/09 | G3: Movimentação | H3: Controlador de movimento (Rigidbody/KCC) | I3: Andar, corrida gradativa (velocidade acumula andando pra frente) e pulo respondendo a momentum. Não usar CharacterController nativo. | J3: Lima | K3: Setup do projeto
A4: T003 | B4: To Do | C4: INEGOCIÁVEL | D4: PROTÓTIPO (20/09) | E4: S1 | F4: 11/09 – 18/09 | G4: Câmera | H4: Câmera 3ª pessoa orbital (Cinemachine) | I4: Distância fixa ao personagem, órbita livre pelo mouse, colisão com parede resolvida. | J4: Lima | K4: Controlador de movimento
A5: T004 | B5: To Do | C5: INEGOCIÁVEL | D5: PROTÓTIPO (20/09) | E5: S1 | F5: 11/09 – 18/09 | G5: Movimentação | H5: Wall run | I5: Detecção por raycast lateral, gravidade ajustada, entrada e saída do estado sem travar. | J5: João Pedro | K5: Controlador de movimento
A6: T005 | B6: To Do | C6: INEGOCIÁVEL | D6: PROTÓTIPO (20/09) | E6: S1 | F6: 11/09 – 18/09 | G6: Movimentação | H6: Agarrar bordas (ledge grab) | I6: Detecção de borda, personagem se segura e sobe. Transição sem teleporte visível. | J6: João Pedro | K6: Controlador de movimento
A7: T006 | B7: To Do | C7: INEGOCIÁVEL | D7: PROTÓTIPO (20/09) | E7: S1 | F7: 11/09 – 18/09 | G7: Viagem no tempo | H7: Troca de período instantânea | I7: Clique esquerdo alterna entre dois estados de cenário (Futuro/Superfuturo) com transição muito breve. Posição do jogador preservada. | J7: Pedro | K7: Setup do projeto
A8: T007 | B8: To Do | C8: INEGOCIÁVEL | D8: PROTÓTIPO (20/09) | E8: S1 | F8: 11/09 – 18/09 | G8: Personagem | H8: Modelo base do personagem principal | I8: Mesh do protagonista (alto, esguio, braços fortes, camisa+suspensórios+gravata) com rig funcional. Textura ainda não necessária. | J8: Gabriel | K8: —
A9: T008 | B9: To Do | C9: INEGOCIÁVEL | D9: PROTÓTIPO (20/09) | E9: S1 | F9: 11/09 – 18/09 | G9: Level Design | H9: Sandbox de teste de mecânicas | I9: Cena cinza com paredes pra wall run, bordas pra ledge grab, vãos e os dois estados de período. Serve pra tunar feel. | J9: Lucas | K9: Troca de período
A10: T009 | B10: To Do | C10: INEGOCIÁVEL | D10: PROTÓTIPO (20/09) | E10: S1 | F10: 11/09 – 18/09 | G10: Level Design | H10: Blockout inicial do Nível 1 (Sala de Máquinas) | I10: Whitebox da planta do andar, igual nos dois períodos. Só volume e circulação, sem detalhe. | J10: André | K10: Sandbox
A11: T010 | B11: To Do | C11: ESSENCIAL | D11: PROTÓTIPO (20/09) | E11: S1 | F11: 11/09 – 18/09 | G11: Movimentação | H11: Vault | I11: Pulo dinâmico por cima de objetos, detectado por altura do obstáculo. | J11: João Pedro | K11: Controlador de movimento
A12: T011 | B12: To Do | C12: ESSENCIAL | D12: PROTÓTIPO (20/09) | E12: S1 | F12: 11/09 – 18/09 | G12: Movimentação | H12: Aterrissagem (roll/landing) | I12: Queda curta = landing; queda alta = roll, sem perder todo o momentum. | J12: João Pedro | K12: Controlador de movimento
... A125: T124 | B125: To Do | C125: DESEJÁVEL | D125: BUILD FINAL (06/12) | E125: S12 | F125: 27/11 – 04/12 | G125: Final B | H125: Controle simultâneo dos dois personagens | I125: Trecho final em que o jogador move os dois em direção à esfera. | J125: Lima | K125: Cutscene do abraço

Sheet Equipe
A1: Membro | B1: Título oficial | C1: Frente principal | D1: Frente secundária | E1: Observações de alocação
A2: André | B2: Level Designer / Art Lead | C2: Construção e blockout dos níveis, obstáculos de cenário | D2: Programação de apoio (coringa) | E2: Coringa técnico: pode absorver programação se alguma frente atrasar. É quem mais entrega volume de nível.
A3: Daniel | B3: Programador e Designer de UI | C3: Menus, HUD, configurações, builds e empacotamento | D3: Infra de projeto, integração | E3: Carga de UI é baixa por ser minimalista. Absorve o papel de build master e integrador — trabalho constante e essencial.
A4: Gabriel | B4: Artista de Personagem e Animação | C4: Modelo e animações do protagonista e do perseguidor | D4: Programação de apoio (coringa) | E4: Carga mais pesada e mais contínua do projeto. Cada movimento novo de parkour é trabalho dele. Proteger esse tempo.
A5: João Pedro | B5: Programador de Parkour / Gameplay | C5: Movimentos de parkour, detecção contextual, itens | D5: Gameplay geral | E5: Escopo hoje é só parkour, mas cabe mais: pode assumir itens, coletáveis e lógica de nível conforme sobrar.
A6: Lucas | B6: Level Designer / Artista 3D | C6: Level design dos 5 níveis, direção criativa, validação | D6: Modelagem de assets 3D | E6: Dono do GDD e das decisões de escopo. Conduz playtests e a decisão de Final A vs B. Evitar alocar em programação pura.
A7: Lima | B7: Programador Lead — Movimentação e Câmera | C7: Controlador de momentum, câmera, IA de perseguição, performance | D7: Arquitetura geral, sistemas | E7: Responsável pelo pilar mais importante do jogo (o feel). Deve iterar continuamente, não entregar e sair.
A8: Matheus | B8: Artista de Cenário e Props 3D | C8: Kits modulares dos 5 andares, set dressing, iluminação | D8: VFX de ambiente | E8: Gargalo de arte do projeto. Priorizar kits modulares cedo — tudo depende deles pra sair do whitebox.
A9: Pedro | B9: Programador de Sistemas Temporais | C9: Troca de período, obstáculos por época, replay/fantasma | D9: Shaders de estado | E9: Dono da mecânica que define o jogo. Também é quem constrói o sistema de replay — base do Final B.
A10: Thiago | B10: Artista 2D (inativo) | C10: Trilha/áudio, apoio 2D, paleta de cores | D10: — | E10: OFF no momento. Tarefas marcadas como 'se retornar'. Se não voltar, áudio precisa ser terceirizado ou usar biblioteca licenciada.

Sheet Painel
A1: PAINEL DE ACOMPANHAMENTO
A2: Os números abaixo se atualizam sozinhos conforme a coluna Status da aba Kanban é preenchida.
A4: POR STATUS | D4: POR PRIORIDADE | H4: POR MARCO DE ENTREGA
A5: Status | B5: Tarefas | D5: Prioridade | E5: Total | F5: Concluídas | H5: Marco | I5: Total | J5: Concluídas
A6: To Do | B6: =COUNTIF(Kanban!$B$2:$B$125,A6) -> 124 | D6: INEGOCIÁVEL | E6: =COUNTIF(Kanban!$C$2:$C$125,D6) -> 52 | F6: =COUNTIFS(Kanban!$C$2:$C$125,D6,Kanban!$B$2:$B$125,"Done") -> 0 | H6: PROTÓTIPO (20/09) | I6: =COUNTIF(Kanban!$D$2:$D$125,H6) -> 17 | J6: =COUNTIFS(Kanban!$D$2:$D$125,H6,Kanban!$B$2:$B$125,"Done") -> 0
A7: Doing | B7: =COUNTIF(Kanban!$B$2:$B$125,A7) -> 0 | D7: ESSENCIAL | E7: =COUNTIF(Kanban!$C$2:$C$125,D7) -> 50 | F7: =COUNTIFS(Kanban!$C$2:$C$125,D7,Kanban!$B$2:$B$125,"Done") -> 0 | H7: Rumo à Intermediária | I7: =COUNTIF(Kanban!$D$2:$D$125,H7) -> 36 | J7: =COUNTIFS(Kanban!$D$2:$D$125,H7,Kanban!$B$2:$B$125,"Done") -> 0
A8: Review | B8: =COUNTIF(Kanban!$B$2:$B$125,A8) -> 0 | D8: RELEVANTE | E8: =COUNTIF(Kanban!$C$2:$C$125,D8) -> 15 | F8: =COUNTIFS(Kanban!$C$2:$C$125,D8,Kanban!$B$2:$B$125,"Done") -> 0 | H8: BUILD INTERMEDIÁRIA (18/10) | I8: =COUNTIF(Kanban!$D$2:$D$125,H8) -> 8 | J8: =COUNTIFS(Kanban!$D$2:$D$125,H8,Kanban!$B$2:$B$125,"Done") -> 0
A9: Done | B9: =COUNTIF(Kanban!$B$2:$B$125,A9) -> 0 | D9: DESEJÁVEL | E9: =COUNTIF(Kanban!$C$2:$C$125,D9) -> 7 | F9: =COUNTIFS(Kanban!$C$2:$C$125,D9,Kanban!$B$2:$B$125,"Done") -> 0 | H9: Rumo à Alpha | I9: =COUNTIF(Kanban!$D$2:$D$125,H9) -> 37 | J9: =COUNTIFS(Kanban!$D$2:$D$125,H9,Kanban!$B$2:$B$125,"Done") -> 0
A10: Late | B10: =COUNTIF(Kanban!$B$2:$B$125,A10) -> 0 | H10: BUILD ALPHA (22/11) | I10: =COUNTIF(Kanban!$D$2:$D$125,H10) -> 8 | J10: =COUNTIFS(Kanban!$D$2:$D$125,H10,Kanban!$B$2:$B$125,"Done") -> 0
A11: TOTAL | B11: =COUNTA(Kanban!$A$2:$A$125) -> 124 | H11: Rumo à Final | I11: =COUNTIF(Kanban!$D$2:$D$125,H11) -> 9 | J11: =COUNTIFS(Kanban!$D$2:$D$125,H11,Kanban!$B$2:$B$125,"Done") -> 0
A12: % concluído | B12: =IFERROR(B9/B11,0) -> 0 | H12: BUILD FINAL (06/12) | I12: =COUNTIF(Kanban!$D$2:$D$125,H12) -> 9 | J12: =COUNTIFS(Kanban!$D$2:$D$125,H12,Kanban!$B$2:$B$125,"Done") -> 0
A15: POR SEMANA | F15: LEGENDA DE PRIORIDADES
A16: Semana | B16: Período | C16: Total | D16: Concluídas | F16: INEGOCIÁVEL | G16: Sem isso a entrega daquele marco não existe. Bloqueia todo o resto.
A17: S1 | B17: 11/09 – 18/09 | C17: =COUNTIF(Kanban!$E$2:$E$125,A17) -> 17 | D17: =COUNTIFS(Kanban!$E$2:$E$125,A17,Kanban!$B$2:$B$125,"Done") -> 0 | F17: ESSENCIAL | G17: A entrega funciona sem, mas fica claramente incompleta.
A18: S2 | B18: 18/09 – 25/09 | C18: =COUNTIF(Kanban!$E$2:$E$125,A18) -> 13 | D18: =COUNTIFS(Kanban!$E$2:$E$125,A18,Kanban!$B$2:$B$125,"Done") -> 0 | F18: RELEVANTE | G18: Melhora bastante a experiência; primeira coisa a adiar se apertar.
A19: S3 | B19: 25/09 – 02/10 | C19: =COUNTIF(Kanban!$E$2:$E$125,A19) -> 12 | D19: =COUNTIFS(Kanban!$E$2:$E$125,A19,Kanban!$B$2:$B$125,"Done") -> 0 | F19: DESEJÁVEL | G19: Cenário ideal. Inclui todo o Final B — só entra se a Alpha fechar limpa.
A20: S4 | B20: 02/10 – 09/10 | C20: =COUNTIF(Kanban!$E$2:$E$125,A20) -> 11 | D20: =COUNTIFS(Kanban!$E$2:$E$125,A20,Kanban!$B$2:$B$125,"Done") -> 0
A21: S5 | B21: 09/10 – 16/10 | C21: =COUNTIF(Kanban!$E$2:$E$125,A21) -> 8 | D21: =COUNTIFS(Kanban!$E$2:$E$125,A21,Kanban!$B$2:$B$125,"Done") -> 0 | F21: COMO USAR
A22: S6 | B22: 16/10 – 23/10 | C22: =COUNTIF(Kanban!$E$2:$E$125,A22) -> 9 | D22: =COUNTIFS(Kanban!$E$2:$E$125,A22,Kanban!$B$2:$B$125,"Done") -> 0 | F22: 1. A aba Kanban é a fonte de verdade. Cada linha é uma tarefa de uma semana específica.
A23: S7 | B23: 23/10 – 30/10 | C23: =COUNTIF(Kanban!$E$2:$E$125,A23) -> 9 | D23: =COUNTIFS(Kanban!$E$2:$E$125,A23,Kanban!$B$2:$B$125,"Done") -> 0 | F23: 2. Mova a tarefa pela coluna Status: To Do → Doing → Review → Done. Use Late quando a semana passar sem concluir.
A24: S8 | B24: 30/10 – 06/11 | C24: =COUNTIF(Kanban!$E$2:$E$125,A24) -> 11 | D24: =COUNTIFS(Kanban!$E$2:$E$125,A24,Kanban!$B$2:$B$125,"Done") -> 0 | F24: 3. Use o filtro do cabeçalho pra ver só uma semana, um responsável ou uma prioridade por vez.
A25: S9 | B25: 06/11 – 13/11 | C25: =COUNTIF(Kanban!$E$2:$E$125,A25) -> 8 | D25: =COUNTIFS(Kanban!$E$2:$E$125,A25,Kanban!$B$2:$B$125,"Done") -> 0 | F25: 4. Este painel se atualiza sozinho — não edite as células de número aqui.
A26: S10 | B26: 13/11 – 20/11 | C26: =COUNTIF(Kanban!$E$2:$E$125,A26) -> 8 | D26: =COUNTIFS(Kanban!$E$2:$E$125,A26,Kanban!$B$2:$B$125,"Done") -> 0 | F26: 5. 'Depende de' indica o que precisa estar pronto antes. Não comece uma tarefa com dependência em aberto.
A27: S11 | B27: 20/11 – 27/11 | C27: =COUNTIF(Kanban!$E$2:$E$125,A27) -> 9 | D27: =COUNTIFS(Kanban!$E$2:$E$125,A27,Kanban!$B$2:$B$125,"Done") -> 0 | F27: 6. A partir da S2, cada semana tem 7 dias corridos, com a entrega da semana anterior e o início da próxima no mesmo dia. Nas semanas de marco, a entrega oficial cai 2 dias depois do fim da semana, como margem de segurança.
A28: S12 | B28: 27/11 – 04/12 | C28: =COUNTIF(Kanban!$E$2:$E$125,A28) -> 9 | D28: =COUNTIFS(Kanban!$E$2:$E$125,A28,Kanban!$B$2:$B$125,"Done") -> 0 | F28: 7. Títulos oficiais de cada pessoa estão na aba Equipe, coluna 'Título oficial' — não aparecem na aba Kanban de propósito, pra manter a tabela enxuta.
